{
  "d_list": [
    {
      "gauging_station": {
        "name": "Nagalagam Street",
        "river": {
          "name": "Kelani Ganga",
          "river_basin": {
            "code": "RB 01",
            "name": "Kelani Ganga"
          }
        },
        "alert_level": {
          "m": 1.2192
        },
        "minor_flood_level": {
          "m": 1.524
        },
        "major_flood_level": {
          "m": 2.1336
        },
        "lat_lng": [
          6.96027242132317,
          79.87858326530204
        ],
        "district_id": "LK-11;LK-12"
      },
      "time_str": "2025-11-28 06:00:00",
      "time_ut": 1764289800,
      "previous_water_level": {
        "m": 0.54864
      },
      "current_water_level": {
        "m": 0.6096
      },
      "remarks": "Normal",
      "rising_or_falling": "",
      "rainfall_mm": 0.0
    },
    {
      "gauging_station": {
        "name": "Hanwella",
        "river": {
          "name": "Kelani Ganga",
          "river_basin": {
            "code": "RB 01",
            "name": "Kelani Ganga"
          }
        },
        "alert_level": {
          "m": 7.0
        },
        "minor_flood_level": {
          "m": 8.0
        },
        "major_flood_level": {
          "m": 10.0
        },
        "lat_lng": [
          6.910489028063102,
          80.08133984391833
        ],
        "district_id": "LK-11"
      },
      "time_str": "2025-11-28 06:00:00",
      "time_ut": 1764289800,
      "previous_water_level": {
        "m": 2.68
      },
      "current_water_level": {
        "m": 2.73
      },
      "remarks": "Normal",
      "rising_or_falling": "",
      "rainfall_mm": 23.6
    },
    {
      "gauging_station": {
        "name": "Glencourse",
        "river": {
          "name": "Kelani Ganga",
          "river_basin": {
            "code": "RB 01",
            "name": "Kelani Ganga"
          }
        },
        "alert_level": {
          "m": 15.0
        },
        "minor_flood_level": {
          "m": 16.5
        },
        "major_flood_level": {
          "m": 19.0
        },
        "lat_lng": [
          6.975736673046383,
          80.18660711562987
        ],
        "district_id": "LK-11;LK-12;LK-92"
      },
      "time_str": "2025-11-28 06:00:00",
      "time_ut": 1764289800,
      "previous_water_level": {
        "m": 11.1
      },
      "current_water_level": {
        "m": 11.18
      },
      "remarks": "Normal",
      "rising_or_falling": "",
      "rainfall_mm": 45.3
    },
    {
      "gauging_station": {
        "name": "Kithulgala",
        "river": {
          "name": "Kelani Ganga",
          "river_basin": {
            "code": "RB 01",
            "name": "Kelani Ganga"
          }
        },
        "alert_level": {
          "m": 3.0
        },
        "minor_flood_level": {
          "m": 4.0
        },
        "major_flood_level": {
          "m": 6.0
        },
        "lat_lng": [
          6.985283769517581,
          80.42544930669654
        ],
        "district_id": "LK-92"
      },
      "time_str": "2025-11-28 06:00:00",
      "time_ut": 1764289800,
      "previous_water_level": {
        "m": 1.83
      },
      "current_water_level": {
        "m": 1.9
      },
      "remarks": "Normal",
      "rising_or_falling": "",
      "rainfall_mm": 67.7
    },
    {
      "gauging_station": {
        "name": "Holombuwa",
        "river": {
          "name": "Gurugoda Oya",
          "river_basin": {
            "code": "RB 01",
            "name": "Kelani Ganga"
          }
        },
        "alert_level": {
          "m": 3.0
        },
        "minor_flood_level": {
          "m": 3.4
        },
        "major_flood_level": {
          "m": 5.0
        },
        "lat_lng": [
          7.18861230041471,
          80.27381001159266
        ],
        "district_id": "LK-92"
      },
      "time_str": "2025-11-28 06:00:00",
      "time_ut": 1764289800,
      "previous_water_level": {
        "m": 2.11
      },
      "current_water_level": {
        "m": 2.71
      },
      "remarks": "Normal",
      "rising_or_falling": "",
      "rainfall_mm": 87.8
    },
    {
      "gauging_station": {
        "name": "Deraniyagala",
        "river": {
          "name": "Seethawaka Ganga",
          "river_basin": {
            "code": "RB 01",
            "name": "Kelani Ganga"
          }
        },
        "alert_level": {
          "m": 4.8
        },
        "minor_flood_level": {
          "m": 5.8
        },
        "major_flood_level": {
          "m": 6.4
        },
        "lat_lng": [
          6.925762947059961,
          80.33922404112188
        ],
        "district_id": "LK-92"
      },
      "time_str": "2025-11-28 06:00:00",
      "time_ut": 1764289800,
      "previous_water_level": {
        "m": 1.08
      },
      "current_water_level": {
        "m": 1.26
      },
      "remarks": "Normal",
      "rising_or_falling": "",
      "rainfall_mm": 69.8
    },
    {
      "gauging_station": {
        "name": "Norwood",
        "river": {
          "name": "Kehelgamu Oya",
          "river_basin": {
            "code": "RB 01",
            "name": "Kelani Ganga"
          }
        },
        "alert_level": {
          "m": 1.5
        },
        "minor_flood_level": {
          "m": 3.0
        },
        "major_flood_level": {
          "m": 4.5
        },
        "lat_lng": [
          6.839557267884663,
          80.61239609102284
        ],
        "district_id": "LK-23"
      },
      "time_str": "2025-11-28 06:00:00",
      "time_ut": 1764289800,
      "previous_water_level": {
        "m": 1.41
      },
      "current_water_level": {
        "m": 1.55
      },
      "remarks": "Alert",
      "rising_or_falling": "Rising",
      "rainfall_mm": 42.6
    },
    {
      "gauging_station": {
        "name": "Putupaula",
        "river": {
          "name": "Kalu Ganga",
          "river_basin": {
            "code": "RB 03",
            "name": "Kalu Ganga"
          }
        },
        "alert_level": {
          "m": 3.0
        },
        "minor_flood_level": {
          "m": 4.0
        },
        "major_flood_level": {
          "m": 5.0
        },
        "lat_lng": [
          6.611561688998894,
          80.05974948036196
        ],
        "district_id": "LK-13"
      },
      "time_str": "2025-11-28 06:00:00",
      "time_ut": 1764289800,
      "previous_water_level": {
        "m": 1.6
      },
      "current_water_level": {
        "m": 1.6
      },
      "remarks": "Normal",
      "rising_or_falling": "",
      "rainfall_mm": 3.8
    },
    {
      "gauging_station": {
        "name": "Ellagawa",
        "river": {
          "name": "Kalu Ganga",
          "river_basin": {
            "code": "RB 03",
            "name": "Kalu Ganga"
          }
        },
        "alert_level": {
          "m": 10.0
        },
        "minor_flood_level": {
          "m": 10.7
        },
        "major_flood_level": {
          "m": 12.2
        },
        "lat_lng": [
          6.730399127799353,
          80.21307042256922
        ],
        "district_id": "LK-91;LK-13"
      },
      "time_str": "2025-11-28 06:00:00",
      "time_ut": 1764289800,
      "previous_water_level": {
        "m": 6.51
      },
      "current_water_level": {
        "m": 6.5
      },
      "remarks": "Normal",
      "rising_or_falling": "",
      "rainfall_mm": 19.0
    },
    {
      "gauging_station": {
        "name": "Rathnapura",
        "river": {
          "name": "Kalu Ganga",
          "river_basin": {
            "code": "RB 03",
            "name": "Kalu Ganga"
          }
        },
        "alert_level": {
          "m": 5.2
        },
        "minor_flood_level": {
          "m": 7.5
        },
        "major_flood_level": {
          "m": 9.5
        },
        "lat_lng": [
          6.689859893761882,
          80.38027645749384
        ],
        "district_id": "LK-91"
      },
      "time_str": "2025-11-28 06:00:00",
      "time_ut": 1764289800,
      "previous_water_level": {
        "m": 2.7
      },
      "current_water_level": {
        "m": 2.78
      },
      "remarks": "Normal",
      "rising_or_falling": "",
      "rainfall_mm": 16.5
    },
    {
      "gauging_station": {
        "name": "Magura",
        "river": {
          "name": "Maguru Ganga",
          "river_basin": {
            "code": "RB 03",
            "name": "Kalu Ganga"
          }
        },
        "alert_level": {
          "m": 4.0
        },
        "minor_flood_level": {
          "m": 6.0
        },
        "major_flood_level": {
          "m": 7.5
        },
        "lat_lng": [
          6.513716270509724,
          80.24399187228877
        ],
        "district_id": "LK-13"
      },
      "time_str": "2025-11-28 06:00:00",
      "time_ut": 1764289800,
      "previous_water_level": {
        "m": 2.81
      },
      "current_water_level": {
        "m": 2.88
      },
      "remarks": "Normal",
      "rising_or_falling": "",
      "rainfall_mm": 13.6
    },
    {
      "gauging_station": {
        "name": "Kalawellawa",
        "river": {
          "name": "Kuda Ganga",
          "river_basin": {
            "code": "RB 03",
            "name": "Kalu Ganga"
          }
        },
        "alert_level": {
          "m": 5.0
        },
        "minor_flood_level": {
          "m": 6.5
        },
        "major_flood_level": {
          "m": 8.0
        },
        "lat_lng": [
          6.6315078194386246,
          80.16073462916866
        ],
        "district_id": "LK-13"
      },
      "time_str": "2025-11-28 06:00:00",
      "time_ut": 1764289800,
      "previous_water_level": {
        "m": 4.81
      },
      "current_water_level": {
        "m": 4.8
      },
      "remarks": "Normal",
      "rising_or_falling": "",
      "rainfall_mm": 8.9
    },
    {
      "gauging_station": {
        "name": "Baddegama",
        "river": {
          "name": "Gin Ganga",
          "river_basin": {
            "code": "RB 09",
            "name": "Gin Ganga"
          }
        },
        "alert_level": {
          "m": 3.5
        },
        "minor_flood_level": {
          "m": 4.0
        },
        "major_flood_level": {
          "m": 5.0
        },
        "lat_lng": [
          6.177477311875031,
          80.18051836126706
        ],
        "district_id": "LK-31"
      },
      "time_str": "2025-11-28 06:00:00",
      "time_ut": 1764289800,
      "previous_water_level": {
        "m": 3.37
      },
      "current_water_level": {
        "m": 3.36
      },
      "remarks": "Normal",
      "rising_or_falling": "",
      "rainfall_mm": 5.2
    },
    {
      "gauging_station": {
        "name": "Thawalama",
        "river": {
          "name": "Gin Ganga",
          "river_basin": {
            "code": "RB 09",
            "name": "Gin Ganga"
          }
        },
        "alert_level": {
          "m": 4.0
        },
        "minor_flood_level": {
          "m": 6.0
        },
        "major_flood_level": {
          "m": 7.5
        },
        "lat_lng": [
          6.342938049010117,
          80.33185946143057
        ],
        "district_id": "LK-31;LK-13"
      },
      "time_str": "2025-11-28 06:00:00",
      "time_ut": 1764289800,
      "previous_water_level": {
        "m": 2.14
      },
      "current_water_level": {
        "m": 2.12
      },
      "remarks": "Normal",
      "rising_or_falling": "",
      "rainfall_mm": 5.9
    },
    {
      "gauging_station": {
        "name": "Thalgahagoda",
        "river": {
          "name": "Nilwala Ganga",
          "river_basin": {
            "code": "RB 12",
            "name": "Nilwala Ganga"
          }
        },
        "alert_level": {
          "m": 1.4
        },
        "minor_flood_level": {
          "m": 1.7
        },
        "major_flood_level": {
          "m": 2.8
        },
        "lat_lng": [
          6.012329836481981,
          80.5347970941782
        ],
        "district_id": "LK-32"
      },
      "time_str": "2025-11-28 06:00:00",
      "time_ut": 1764289800,
      "previous_water_level": {
        "m": 1.58
      },
      "current_water_level": {
        "m": 1.58
      },
      "remarks": "Alert",
      "rising_or_falling": "",
      "rainfall_mm": 72.4
    },
    {
      "gauging_station": {
        "name": "Panadugama",
        "river": {
          "name": "Nilwala Ganga",
          "river_basin": {
            "code": "RB 12",
            "name": "Nilwala Ganga"
          }
        },
        "alert_level": {
          "m": 5.0
        },
        "minor_flood_level": {
          "m": 6.0
        },
        "major_flood_level": {
          "m": 7.5
        },
        "lat_lng": [
          6.1100549018149115,
          80.48065133051018
        ],
        "district_id": "LK-32"
      },
      "time_str": "2025-11-28 06:00:00",
      "time_ut": 1764289800,
      "previous_water_level": {
        "m": 4.84
      },
      "current_water_level": {
        "m": 4.96
      },
      "remarks": "Normal",
      "rising_or_falling": "",
      "rainfall_mm": 49.9
    },
    {
      "gauging_station": {
        "name": "Pitabeddara",
        "river": {
          "name": "Nilwala Ganga",
          "river_basin": {
            "code": "RB 12",
            "name": "Nilwala Ganga"
          }
        },
        "alert_level": {
          "m": 4.0
        },
        "minor_flood_level": {
          "m": 5.0
        },
        "major_flood_level": {
          "m": 6.5
        },
        "lat_lng": [
          6.20712968715078,
          80.45044348808202
        ],
        "district_id": "LK-32"
      },
      "time_str": "2025-11-28 06:00:00",
      "time_ut": 1764289800,
      "previous_water_level": {
        "m": 2.57
      },
      "current_water_level": {
        "m": 2.77
      },
      "remarks": "Normal",
      "rising_or_falling": "",
      "rainfall_mm": 37.8
    },
    {
      "gauging_station": {
        "name": "Urawa",
        "river": {
          "name": "Urubokka Ganga",
          "river_basin": {
            "code": "RB 12",
            "name": "Nilwala Ganga"
          }
        },
        "alert_level": {
          "m": 2.5
        },
        "minor_flood_level": {
          "m": 4.0
        },
        "major_flood_level": {
          "m": 6.0
        },
        "lat_lng": [
          6.236507396306039,
          80.56633784106945
        ],
        "district_id": "LK-32"
      },
      "time_str": "2025-11-28 06:00:00",
      "time_ut": 1764289800,
      "previous_water_level": {
        "m": 2.84
      },
      "current_water_level": {
        "m": 2.72
      },
      "remarks": "Alert",
      "rising_or_falling": "Falling",
      "rainfall_mm": 83.1
    },
    {
      "gauging_station": {
        "name": "Moraketiya",
        "river": {
          "name": "Walawe Ganga",
          "river_basin": {
            "code": "RB 18",
            "name": "Walawe Ganga"
          }
        },
        "alert_level": {
          "m": 3.0
        },
        "minor_flood_level": {
          "m": 5.0
        },
        "major_flood_level": {
          "m": 7.0
        },
        "lat_lng": [
          6.3450504078771,
          80.90195373048093
        ],
        "district_id": "LK-91;LK-82"
      },
      "time_str": "2025-11-28 06:00:00",
      "time_ut": 1764289800,
      "previous_water_level": {
        "m": 1.2
      },
      "current_water_level": {
        "m": 1.2
      },
      "remarks": "Normal",
      "rising_or_falling": "",
      "rainfall_mm": 1.2
    },
    {
      "gauging_station": {
        "name": "Thanamalwila",
        "river": {
          "name": "Kirindi Oya",
          "river_basin": {
            "code": "RB 22",
            "name": "Kirindi Oya"
          }
        },
        "alert_level": {
          "m": 4.0
        },
        "minor_flood_level": {
          "m": 5.0
        },
        "major_flood_level": {
          "m": 5.5
        },
        "lat_lng": [
          6.44280954004885,
          81.13889314602751
        ],
        "district_id": "LK-82"
      },
      "time_str": "2025-11-28 06:00:00",
      "time_ut": 1764289800,
      "previous_water_level": {
        "m": 2.6
      },
      "current_water_level": {
        "m": 2.65
      },
      "remarks": "Normal",
      "rising_or_falling": "",
      "rainfall_mm": 11.6
    },
    {
      "gauging_station": {
        "name": "Wellawaya",
        "river": {
          "name": "Kirindi Oya",
          "river_basin": {
            "code": "RB 22",
            "name": "Kirindi Oya"
          }
        },
        "alert_level": {
          "m": 4.4
        },
        "minor_flood_level": {
          "m": 5.4
        },
        "major_flood_level": {
          "m": 5.9
        },
        "lat_lng": [
          6.733186416118142,
          81.10987205932976
        ],
        "district_id": "LK-82"
      },
      "time_str": "2025-11-28 06:00:00",
      "time_ut": 1764289800,
      "previous_water_level": {
        "m": 2.04
      },
      "current_water_level": {
        "m": 1.98
      },
      "remarks": "Normal",
      "rising_or_falling": "",
      "rainfall_mm": 26.9
    },
    {
      "gauging_station": {
        "name": "Kuda Oya",
        "river": {
          "name": "Kuda Oya",
          "river_basin": {
            "code": "RB 22",
            "name": "Kirindi Oya"
          }
        },
        "alert_level": {
          "m": 6.9
        },
        "minor_flood_level": {
          "m": 8.4
        },
        "major_flood_level": {
          "m": 8.8
        },
        "lat_lng": [
          6.531299778512797,
          81.11931312403397
        ],
        "district_id": "LK-82"
      },
      "time_str": "2025-11-28 06:00:00",
      "time_ut": 1764289800,
      "previous_water_level": {
        "m": 2.45
      },
      "current_water_level": {
        "m": 2.5
      },
      "remarks": "Normal",
      "rising_or_falling": "",
      "rainfall_mm": 11.5
    },
    {
      "gauging_station": {
        "name": "Katharagama",
        "river": {
          "name": "Menik Ganga",
          "river_basin": {
            "code": "RB 26",
            "name": "Menik Ganga"
          }
        },
        "alert_level": {
          "m": 4.0
        },
        "minor_flood_level": {
          "m": 4.6
        },
        "major_flood_level": {
          "m": 6.5
        },
        "lat_lng": [
          6.418350424146931,
          81.33162402101244
        ],
        "district_id": "LK-82"
      },
      "time_str": "2025-11-28 06:00:00",
      "time_ut": 1764289800,
      "previous_water_level": {
        "m": 2.65
      },
      "current_water_level": {
        "m": 2.63
      },
      "remarks": "Normal",
      "rising_or_falling": "",
      "rainfall_mm": 29.2
    },
    {
      "gauging_station": {
        "name": "Nakkala",
        "river": {
          "name": "Kumbukkan Oya",
          "river_basin": {
            "code": "RB 31",
            "name": "Kumbukkan Oya"
          }
        },
        "alert_level": {
          "m": 5.0
        },
        "minor_flood_level": {
          "m": 6.0
        },
        "major_flood_level": {
          "m": 7.5
        },
        "lat_lng": [
          6.890291115719028,
          81.29789316071579
        ],
        "district_id": "LK-82"
      },
      "time_str": "2025-11-28 06:00:00",
      "time_ut": 1764289800,
      "previous_water_level": {
        "m": 4.66
      },
      "current_water_level": {
        "m": 4.36
      },
      "remarks": "Normal",
      "rising_or_falling": "",
      "rainfall_mm": 75.3
    },
    {
      "gauging_station": {
        "name": "Siyambalanduwa",
        "river": {
          "name": "Heda Oya",
          "river_basin": {
            "code": "RB 36",
            "name": "Heda Oya"
          }
        },
        "alert_level": {
          "m": 4.5
        },
        "minor_flood_level": {
          "m": 6.0
        },
        "major_flood_level": {
          "m": 7.0
        },
        "lat_lng": [
          6.905508688496518,
          81.54537666124355
        ],
        "district_id": "LK-82"
      },
      "time_str": "2025-11-28 06:00:00",
      "time_ut": 1764289800,
      "previous_water_level": {
        "m": 5.52
      },
      "current_water_level": {
        "m": 5.03
      },
      "remarks": "Alert",
      "rising_or_falling": "Falling",
      "rainfall_mm": 87.9
    },
    {
      "gauging_station": {
        "name": "Padiyathalawa",
        "river": {
          "name": "Maduru Oya",
          "river_basin": {
            "code": "RB 54",
            "name": "Maduru Oya"
          }
        },
        "alert_level": {
          "m": 4.0
        },
        "minor_flood_level": {
          "m": 4.5
        },
        "major_flood_level": {
          "m": 6.0
        },
        "lat_lng": [
          7.3827145879708445,
          81.19476999029227
        ],
        "district_id": "LK-81;LK-52"
      },
      "time_str": "2025-11-28 06:00:00",
      "time_ut": 1764289800,
      "previous_water_level": {
        "m": 5.61
      },
      "current_water_level": {
        "m": 5.7
      },
      "remarks": "Minor Flood",
      "rising_or_falling": "Rising",
      "rainfall_mm": 104.1
    },
    {
      "gauging_station": {
        "name": "Manampitiya",
        "river": {
          "name": "Mahaweli Ganga",
          "river_basin": {
            "code": "RB 60",
            "name": "Mahaweli Ganga"
          }
        },
        "alert_level": {
          "m": 3.0
        },
        "minor_flood_level": {
          "m": 4.3
        },
        "major_flood_level": {
          "m": 6.0
        },
        "lat_lng": [
          7.913305747028369,
          81.08904162459265
        ],
        "district_id": "LK-72"
      },
      "time_str": "2025-11-28 06:00:00",
      "time_ut": 1764289800,
      "previous_water_level": {
        "m": 5.1
      },
      "current_water_level": {
        "m": 5.15
      },
      "remarks": "Minor Flood",
      "rising_or_falling": "Rising",
      "rainfall_mm": 168.0
    },
    {
      "gauging_station": {
        "name": "Weraganthota",
        "river": {
          "name": "Mahaweli Ganga",
          "river_basin": {
            "code": "RB 60",
            "name": "Mahaweli Ganga"
          }
        },
        "alert_level": {
          "m": 5.0
        },
        "minor_flood_level": {
          "m": 6.0
        },
        "major_flood_level": {
          "m": 8.0
        },
        "lat_lng": [
          7.329958849723429,
          80.98789578050872
        ],
        "district_id": "LK-21;LK-81"
      },
      "time_str": "2025-11-28 06:00:00",
      "time_ut": 1764289800,
      "previous_water_level": {
        "m": 3.62
      },
      "current_water_level": {
        "m": 3.7
      },
      "remarks": "Normal",
      "rising_or_falling": "",
      "rainfall_mm": 135.4
    },
    {
      "gauging_station": {
        "name": "Peradeniya",
        "river": {
          "name": "Mahaweli Ganga",
          "river_basin": {
            "code": "RB 60",
            "name": "Mahaweli Ganga"
          }
        },
        "alert_level": {
          "m": 5.0
        },
        "minor_flood_level": {
          "m": 7.0
        },
        "major_flood_level": {
          "m": 9.0
        },
        "lat_lng": [
          7.2641705575045075,
          80.5936236622826
        ],
        "district_id": "LK-21"
      },
      "time_str": "2025-11-28 06:00:00",
      "time_ut": 1764289800,
      "previous_water_level": {
        "m": 6.2
      },
      "current_water_level": {
        "m": 6.67
      },
      "remarks": "Alert",
      "rising_or_falling": "Rising",
      "rainfall_mm": 117.3
    },
    {
      "gauging_station": {
        "name": "Nawalapitiya",
        "river": {
          "name": "Mahaweli Ganga",
          "river_basin": {
            "code": "RB 60",
            "name": "Mahaweli Ganga"
          }
        },
        "alert_level": {
          "m": 3.5
        },
        "minor_flood_level": {
          "m": 5.0
        },
        "major_flood_level": {
          "m": 6.0
        },
        "lat_lng": [
          7.046038718801128,
          80.52624731051829
        ],
        "district_id": "LK-21"
      },
      "time_str": "2025-11-28 06:00:00",
      "time_ut": 1764289800,
      "previous_water_level": {
        "m": 2.2
      },
      "current_water_level": {
        "m": 2.8
      },
      "remarks": "Normal",
      "rising_or_falling": "",
      "rainfall_mm": 76.9
    },
    {
      "gauging_station": {
        "name": "Thaldena",
        "river": {
          "name": "Badulu Oya",
          "river_basin": {
            "code": "RB 60",
            "name": "Mahaweli Ganga"
          }
        },
        "alert_level": {
          "m": 3.0
        },
        "minor_flood_level": {
          "m": 4.0
        },
        "major_flood_level": {
          "m": 5.0
        },
        "lat_lng": [
          7.092702894310825,
          81.04865409851845
        ],
        "district_id": "LK-81"
      },
      "time_str": "2025-11-28 06:00:00",
      "time_ut": 1764289800,
      "previous_water_level": {
        "m": 2.95
      },
      "current_water_level": {
        "m": 2.75
      },
      "remarks": "Normal",
      "rising_or_falling": "",
      "rainfall_mm": 114.0
    },
    {
      "gauging_station": {
        "name": "Horowpothana",
        "river": {
          "name": "Yan Oya",
          "river_basin": {
            "code": "RB 67",
            "name": "Yan Oya"
          }
        },
        "alert_level": {
          "m": 6.0
        },
        "minor_flood_level": {
          "m": 7.5
        },
        "major_flood_level": {
          "m": 10.5
        },
        "lat_lng": [
          8.577144224946247,
          80.88120305584708
        ],
        "district_id": "LK-71"
      },
      "time_str": "2025-11-28 06:00:00",
      "time_ut": 1764289800,
      "previous_water_level": {
        "m": 7.56
      },
      "current_water_level": {
        "m": 7.58
      },
      "remarks": "Minor Flood",
      "rising_or_falling": "Rising",
      "rainfall_mm": 73.2
    },
    {
      "gauging_station": {
        "name": "Yaka Wewa",
        "river": {
          "name": "Mukunu Oya",
          "river_basin": {
            "code": "RB 69",
            "name": "Maa Oya"
          }
        },
        "alert_level": {
          "m": 4.0
        },
        "minor_flood_level": {
          "m": 5.0
        },
        "major_flood_level": {
          "m": 6.0
        },
        "lat_lng": [
          8.726531670464757,
          80.67505377972024
        ],
        "district_id": "LK-61"
      },
      "time_str": "2025-11-28 06:00:00",
      "time_ut": 1764289800,
      "previous_water_level": {
        "m": 5.23
      },
      "current_water_level": {
        "m": 5.16
      },
      "remarks": "Minor Flood",
      "rising_or_falling": "Falling",
      "rainfall_mm": 140.8
    },
    {
      "gauging_station": {
        "name": "Thanthirimale",
        "river": {
          "name": "Malwathu Oya",
          "river_basin": {
            "code": "RB 90",
            "name": "Malwathu Oya"
          }
        },
        "alert_level": {
          "m": 5.0
        },
        "minor_flood_level": {
          "m": 6.8
        },
        "major_flood_level": {
          "m": 7.8
        },
        "lat_lng": [
          8.580763249784683,
          80.28400551575419
        ],
        "district_id": "LK-71;LK-43"
      },
      "time_str": "2025-11-28 06:00:00",
      "time_ut": 1764289800,
      "previous_water_level": {
        "m": 5.62
      },
      "current_water_level": {
        "m": 5.7
      },
      "remarks": "Alert",
      "rising_or_falling": "Rising",
      "rainfall_mm": 94.5
    },
    {
      "gauging_station": {
        "name": "Moragaswewa",
        "river": {
          "name": "Deduru Oya",
          "river_basin": {
            "code": "RB 99",
            "name": "Deduru Oya"
          }
        },
        "alert_level": {
          "m": 4.75
        },
        "minor_flood_level": {
          "m": 6.0
        },
        "major_flood_level": {
          "m": 7.0
        },
        "lat_lng": [
          7.731867586461941,
          80.24296279159842
        ],
        "district_id": "LK-61"
      },
      "time_str": "2025-11-28 06:00:00",
      "time_ut": 1764289800,
      "previous_water_level": {
        "m": 4.53
      },
      "current_water_level": {
        "m": 4.78
      },
      "remarks": "Alert",
      "rising_or_falling": "Rising",
      "rainfall_mm": 51.8
    },
    {
      "gauging_station": {
        "name": "Badalgama",
        "river": {
          "name": "Maha Oya",
          "river_basin": {
            "code": "RB 102",
            "name": "Maha Oya"
          }
        },
        "alert_level": {
          "m": 5.0
        },
        "minor_flood_level": {
          "m": 6.2
        },
        "major_flood_level": {
          "m": 9.6
        },
        "lat_lng": [
          7.2931279607144255,
          79.97767925329397
        ],
        "district_id": "LK-62;LK-61;LK-12"
      },
      "time_str": "2025-11-28 06:00:00",
      "time_ut": 1764289800,
      "previous_water_level": {
        "m": 4.22
      },
      "current_water_level": {
        "m": 4.3
      },
      "remarks": "Normal",
      "rising_or_falling": "",
      "rainfall_mm": 43.9
    },
    {
      "gauging_station": {
        "name": "Giriulla",
        "river": {
          "name": "Maha Oya",
          "river_basin": {
            "code": "RB 102",
            "name": "Maha Oya"
          }
        },
        "alert_level": {
          "m": 5.5
        },
        "minor_flood_level": {
          "m": 6.5
        },
        "major_flood_level": {
          "m": 7.5
        },
        "lat_lng": [
          7.3303094121475345,
          80.12432086937476
        ],
        "district_id": "LK-61"
      },
      "time_str": "2025-11-28 06:00:00",
      "time_ut": 1764289800,
      "previous_water_level": {
        "m": 3.95
      },
      "current_water_level": {
        "m": 4.02
      },
      "remarks": "Normal",
      "rising_or_falling": "",
      "rainfall_mm": 66.8
    },
    {
      "gauging_station": {
        "name": "Dunamale",
        "river": {
          "name": "Attanagalu Oya",
          "river_basin": {
            "code": "RB 103",
            "name": "Attanagalu Oya"
          }
        },
        "alert_level": {
          "m": 3.3
        },
        "minor_flood_level": {
          "m": 4.4
        },
        "major_flood_level": {
          "m": 5.5
        },
        "lat_lng": [
          7.113033305509533,
          80.07900097051707
        ],
        "district_id": "LK-12"
      },
      "time_str": "2025-11-28 06:00:00",
      "time_ut": 1764289800,
      "previous_water_level": {
        "m": 2.53
      },
      "current_water_level": {
        "m": 2.56
      },
      "remarks": "Normal",
      "rising_or_falling": "",
      "rainfall_mm": 42.9
    }
  ]
}